acquisitions/__init__.py
acquisitions/admin.py
acquisitions/apps.py
acquisitions/mixins.py
acquisitions/models.py
acquisitions/settings.py
acquisitions/signals.py
acquisitions/urls.py
acquisitions/api/__init__.py
acquisitions/api/permissions.py
acquisitions/api/serializers.py
acquisitions/api/urls.py
acquisitions/api/viewsets.py
acquisitions/backends/__init__.py
acquisitions/backends/base.py
acquisitions/backends/email/__init__.py
acquisitions/backends/email/django_email.py
acquisitions/backends/sms/__init__.py
acquisitions/backends/sms/console.py
acquisitions/backends/sms/twilio.py
acquisitions/migrations/0001_initial.py
acquisitions/migrations/__init__.py
acquisitions/services/__init__.py
acquisitions/services/communication.py
acquisitions/services/dashboard.py
acquisitions/services/onboarding.py
acquisitions/services/outreach.py
acquisitions/tasks/__init__.py
acquisitions/tasks/outreach_tasks.py
acquisitions/tasks/reminder_tasks.py
acquisitions/templates/admin/acquisitions/app_index.html
acquisitions/templates/admin/acquisitions/dashboard.html
acquisitions/templates/admin/acquisitions/index_with_dashboard.html
acquisitions/templates/admin/acquisitions/prospectiveclient/change_list.html
django_acquisitions-0.1.0.dist-info/METADATA
django_acquisitions-0.1.0.dist-info/WHEEL
django_acquisitions-0.1.0.dist-info/licenses/LICENSE
django_acquisitions-0.1.0.dist-info/RECORD
