Metadata-Version: 2.4
Name: django-acquisitions
Version: 0.1.0
Summary: Django customer acquisition pipeline for managing leads, outreach, and onboarding
Project-URL: Homepage, https://github.com/specialorange/django-acquisitions
Project-URL: Repository, https://github.com/specialorange/django-acquisitions
Project-URL: Documentation, https://django-acquisitions.readthedocs.io
Author: specialorange
License-Expression: BSD-3-Clause
License-File: LICENSE
Classifier: Development Status :: 3 - Alpha
Classifier: Environment :: Web Environment
Classifier: Framework :: Django
Classifier: Framework :: Django :: 4.2
Classifier: Framework :: Django :: 5.0
Classifier: Framework :: Django :: 5.1
Classifier: Framework :: Django :: 5.2
Classifier: Intended Audience :: Developers
Classifier: License :: OSI Approved :: BSD License
Classifier: Operating System :: OS Independent
Classifier: Programming Language :: Python
Classifier: Programming Language :: Python :: 3
Classifier: Programming Language :: Python :: 3.10
Classifier: Programming Language :: Python :: 3.11
Classifier: Programming Language :: Python :: 3.12
Classifier: Programming Language :: Python :: 3.13
Classifier: Topic :: Software Development :: Libraries :: Python Modules
Requires-Python: >=3.10
Requires-Dist: django>=4.2
Provides-Extra: all
Requires-Dist: celery>=5.0; extra == 'all'
Requires-Dist: djangorestframework>=3.14; extra == 'all'
Requires-Dist: twilio>=8.0; extra == 'all'
Provides-Extra: celery
Requires-Dist: celery>=5.0; extra == 'celery'
Provides-Extra: docs
Requires-Dist: furo>=2024.0; extra == 'docs'
Requires-Dist: sphinx>=7.0; extra == 'docs'
Provides-Extra: drf
Requires-Dist: djangorestframework>=3.14; extra == 'drf'
Provides-Extra: twilio
Requires-Dist: twilio>=8.0; extra == 'twilio'
